databasedrivers/Configs/Classes/SQLConfigClass.py
databasedrivers/Configs/Classes/__init__.py
databasedrivers/Configs/Dictonaries/SQLConfigDictionary.py
databasedrivers/Configs/Dictonaries/__init__.py
databasedrivers/Configs/__init__.py
databasedrivers/Connectors/MySQLConnector.py
databasedrivers/Connectors/__init__.py
databasedrivers/Interfaces/SQLInterface.py
databasedrivers/Interfaces/__init__.py
databasedrivers/__init__.py
databasedrivers-0.1.0.dist-info/LICENSE
databasedrivers-0.1.0.dist-info/WHEEL
databasedrivers-0.1.0.dist-info/METADATA
databasedrivers-0.1.0.dist-info/RECORD
