Metadata-Version: 2.1
Name: databasedrivers
Version: 0.1.0
Summary: 
License: MIT
Author: ptabis
Author-email: p.tabis@protonmail.com
Requires-Python: >=3.9,<4.0
Classifier: License :: OSI Approved :: MIT License
Classifier: Programming Language :: Python :: 3
Classifier: Programming Language :: Python :: 3.9
Requires-Dist: mysql-connector-python (>=8.0.26,<9.0.0)
